hanpy/__init__.py
hanpy-0.1.0.dist-info/METADATA
hanpy-0.1.0.dist-info/WHEEL
hanpy-0.1.0.dist-info/RECORD
