Metadata-Version: 2.1
Name: hanpy
Version: 0.1.0
Summary: Hanpy is a Python-compatible language that enables programming in Korean.
License: MIT
Author: ilotoki0804
Author-email: ilotoki0804@gmail.com
Requires-Python: >=3.11,<4.0
Classifier: License :: OSI Approved :: MIT License
Classifier: Programming Language :: Python :: 3
Classifier: Programming Language :: Python :: 3.11
Classifier: Programming Language :: Python :: 3.12
